llm_tool_fusion/__init__.py
llm_tool_fusion/_core.py
llm_tool_fusion/_utils.py
llm_tool_fusion-0.2.1.dist-info/licenses/LICENSE
llm_tool_fusion-0.2.1.dist-info/METADATA
llm_tool_fusion-0.2.1.dist-info/WHEEL
llm_tool_fusion-0.2.1.dist-info/top_level.txt
llm_tool_fusion-0.2.1.dist-info/RECORD
