Metadata-Version: 2.4
Name: llm-tool-fusion
Version: 0.2.1
Summary: Biblioteca Python que simplifica e unifica a definição e chamada de ferramentas para grandes modelos de linguagem (LLMs). Compatível com Ollama, LangChain, OpenAI e outros frameworks.
Home-page: https://github.com/caua1503/llm-tool-fusion
Author: Caua ramos
Author-email: cauamedinax@gmail.com
Requires-Python: >=3.12
License-File: LICENSE
Dynamic: author
Dynamic: author-email
Dynamic: home-page
Dynamic: license-file
